{
    "antibiotic": "Minocycline",
    "site": "DRIAMS-A",
    "year": [
        "2015",
        "2016",
        "2017",
        "2018"
    ],
    "positive class ratio": 0.2972972972972973,
    "number spectra with AMR profile": 74,
    "species": [
        "Corynebacterium jeikeium",
        "Acinetobacter baumannii",
        "Corynebacterium tuberculostearicum",
        "Acinetobacter baumannii",
        "Corynebacterium tuberculostearicum",
        "Staphylococcus epidermidis",
        "Staphylococcus epidermidis",
        "Nocardia veterana",
        "MIX!Acinetobacter baumannii",
        "Streptococcus oralis",
        "Corynebacterium tuberculostearicum",
        "Nocardia sp",
        "Nocardia sp",
        "Corynebacterium jeikeium",
        "Nocardia veterana",
        "Acinetobacter baumannii",
        "Stenotrophomonas maltophilia",
        "Acinetobacter baumannii",
        "Stenotrophomonas maltophilia",
        "Stenotrophomonas maltophilia",
        "MIX!Acinetobacter baumannii",
        "Nocardia blacklockiae",
        "Staphylococcus epidermidis",
        "Staphylococcus epidermidis",
        "Staphylococcus epidermidis",
        "Staphylococcus epidermidis",
        "Staphylococcus epidermidis",
        "Burkholderia vietnamiensis",
        "Finegoldia magna",
        "Burkholderia vietnamiensis",
        "Stenotrophomonas maltophilia",
        "Stenotrophomonas maltophilia",
        "Stenotrophomonas maltophilia",
        "Stenotrophomonas maltophilia",
        "Nocardia blacklockiae",
        "Staphylococcus epidermidis",
        "Actinomyces odontolyticus",
        "Burkholderia multivorans",
        "Burkholderia multivorans",
        "Burkholderia multivorans",
        "Burkholderia multivorans",
        "Burkholderia vietnamiensis",
        "MIX!Acinetobacter baumannii",
        "MIX!Acinetobacter baumannii",
        "Burkholderia multivorans",
        "Burkholderia multivorans",
        "Staphylococcus epidermidis",
        "Staphylococcus epidermidis",
        "Burkholderia multivorans",
        "Burkholderia vietnamiensis",
        "Enterococcus faecium",
        "Staphylococcus epidermidis",
        "Burkholderia vietnamiensis",
        "Staphylococcus epidermidis",
        "Staphylococcus epidermidis",
        "Staphylococcus epidermidis",
        "Staphylococcus epidermidis",
        "Staphylococcus epidermidis",
        "Staphylococcus epidermidis",
        "Klebsiella pneumoniae",
        "Acinetobacter baumannii",
        "Acinetobacter baumannii",
        "Burkholderia multivorans",
        "Burkholderia multivorans",
        "Staphylococcus epidermidis",
        "Staphylococcus epidermidis",
        "Staphylococcus epidermidis",
        "Staphylococcus epidermidis",
        "Staphylococcus epidermidis",
        "Staphylococcus epidermidis",
        "Staphylococcus epidermidis",
        "Staphylococcus epidermidis",
        "Burkholderia vietnamiensis",
        "Burkholderia multivorans"
    ],
    "most frequent species": [
        "Staphylococcus epidermidis",
        "Burkholderia multivorans",
        "Stenotrophomonas maltophilia",
        "Acinetobacter baumannii",
        "Burkholderia vietnamiensis"
    ],
    "most frequent species counts": [
        25,
        10,
        7,
        6,
        6
    ]
}