{
    "site": "DRIAMS-A",
    "seed": 270,
    "model": "rf",
    "antibiotic": "5-Fluorocytosine",
    "years": [
        "2015",
        "2016",
        "2017",
        "2018"
    ],
    "metadata_versions": {
        "2015_strat.csv": "a0e7fe7727fbc89833cd7cb04bdb1d6413937218",
        "2016_strat.csv": "c50e25ad41970395d68b5484356ca6f7d343e2e4",
        "2017_strat.csv": "640e67f6c2d3ae60c0bfbe45b420a1abdd619ce9",
        "2018_strat.csv": "2e92914e2032079bcad5fbdd5df04b0020d2ef95"
    },
    "species": "all",
    "spectra_type": "binned_6000",
    "test_size_obtained": 0.20182094081942337,
    "prevalence_train": [
        0.967680608365019,
        0.03231939163498099
    ],
    "prevalence_test": [
        0.9624060150375939,
        0.03759398496240601
    ],
    "best_params": {
        "rf__bootstrap": true,
        "rf__criterion": "entropy",
        "rf__max_features": "log2",
        "rf__n_estimators": 100,
        "rf__oob_score": true
    },
    "y_score": [
        [
            0.97,
            0.03
        ],
        [
            1.0,
            0.0
        ],
        [
            0.97,
            0.03
        ],
        [
            0.98,
            0.02
        ],
        [
            0.97,
            0.03
        ],
        [
            0.99,
            0.01
        ],
        [
            1.0,
            0.0
        ],
        [
            0.97,
            0.03
        ],
        [
            0.99,
            0.01
        ],
        [
            0.98,
            0.02
        ],
        [
            0.91,
            0.09
        ],
        [
            1.0,
            0.0
        ],
        [
            0.98,
            0.02
        ],
        [
            0.99,
            0.01
        ],
        [
            1.0,
            0.0
        ],
        [
            0.99,
            0.01
        ],
        [
            1.0,
            0.0
        ],
        [
            0.97,
            0.03
        ],
        [
            0.92,
            0.08
        ],
        [
            1.0,
            0.0
        ],
        [
            1.0,
            0.0
        ],
        [
            1.0,
            0.0
        ],
        [
            0.99,
            0.01
        ],
        [
            1.0,
            0.0
        ],
        [
            0.95,
            0.05
        ],
        [
            0.99,
            0.01
        ],
        [
            1.0,
            0.0
        ],
        [
            0.99,
            0.01
        ],
        [
            0.92,
            0.08
        ],
        [
            1.0,
            0.0
        ],
        [
            1.0,
            0.0
        ],
        [
            0.94,
            0.06
        ],
        [
            0.94,
            0.06
        ],
        [
            0.98,
            0.02
        ],
        [
            0.98,
            0.02
        ],
        [
            0.98,
            0.02
        ],
        [
            1.0,
            0.0
        ],
        [
            1.0,
            0.0
        ],
        [
            0.94,
            0.06
        ],
        [
            0.94,
            0.06
        ],
        [
            0.99,
            0.01
        ],
        [
            1.0,
            0.0
        ],
        [
            0.99,
            0.01
        ],
        [
            0.99,
            0.01
        ],
        [
            0.96,
            0.04
        ],
        [
            0.99,
            0.01
        ],
        [
            0.99,
            0.01
        ],
        [
            0.97,
            0.03
        ],
        [
            0.56,
            0.44
        ],
        [
            0.98,
            0.02
        ],
        [
            0.97,
            0.03
        ],
        [
            0.99,
            0.01
        ],
        [
            0.99,
            0.01
        ],
        [
            1.0,
            0.0
        ],
        [
            0.99,
            0.01
        ],
        [
            0.99,
            0.01
        ],
        [
            0.98,
            0.02
        ],
        [
            0.93,
            0.07
        ],
        [
            0.97,
            0.03
        ],
        [
            0.99,
            0.01
        ],
        [
            0.96,
            0.04
        ],
        [
            1.0,
            0.0
        ],
        [
            0.99,
            0.01
        ],
        [
            0.99,
            0.01
        ],
        [
            0.82,
            0.18
        ],
        [
            1.0,
            0.0
        ],
        [
            1.0,
            0.0
        ],
        [
            0.98,
            0.02
        ],
        [
            0.87,
            0.13
        ],
        [
            1.0,
            0.0
        ],
        [
            1.0,
            0.0
        ],
        [
            0.98,
            0.02
        ],
        [
            0.99,
            0.01
        ],
        [
            1.0,
            0.0
        ],
        [
            1.0,
            0.0
        ],
        [
            0.97,
            0.03
        ],
        [
            0.99,
            0.01
        ],
        [
            0.93,
            0.07
        ],
        [
            0.99,
            0.01
        ],
        [
            0.97,
            0.03
        ],
        [
            1.0,
            0.0
        ],
        [
            0.97,
            0.03
        ],
        [
            0.96,
            0.04
        ],
        [
            1.0,
            0.0
        ],
        [
            0.97,
            0.03
        ],
        [
            1.0,
            0.0
        ],
        [
            0.99,
            0.01
        ],
        [
            1.0,
            0.0
        ],
        [
            1.0,
            0.0
        ],
        [
            1.0,
            0.0
        ],
        [
            0.81,
            0.19
        ],
        [
            1.0,
            0.0
        ],
        [
            0.89,
            0.11
        ],
        [
            0.98,
            0.02
        ],
        [
            0.99,
            0.01
        ],
        [
            0.9,
            0.1
        ],
        [
            0.82,
            0.18
        ],
        [
            0.97,
            0.03
        ],
        [
            1.0,
            0.0
        ],
        [
            1.0,
            0.0
        ],
        [
            1.0,
            0.0
        ],
        [
            1.0,
            0.0
        ],
        [
            0.98,
            0.02
        ],
        [
            0.96,
            0.04
        ],
        [
            0.99,
            0.01
        ],
        [
            0.92,
            0.08
        ],
        [
            0.99,
            0.01
        ],
        [
            0.99,
            0.01
        ],
        [
            1.0,
            0.0
        ],
        [
            0.98,
            0.02
        ],
        [
            1.0,
            0.0
        ],
        [
            1.0,
            0.0
        ],
        [
            1.0,
            0.0
        ],
        [
            0.97,
            0.03
        ],
        [
            0.99,
            0.01
        ],
        [
            0.99,
            0.01
        ],
        [
            0.97,
            0.03
        ],
        [
            1.0,
            0.0
        ],
        [
            0.99,
            0.01
        ],
        [
            0.99,
            0.01
        ],
        [
            0.97,
            0.03
        ],
        [
            0.99,
            0.01
        ],
        [
            0.9,
            0.1
        ],
        [
            0.97,
            0.03
        ],
        [
            1.0,
            0.0
        ],
        [
            1.0,
            0.0
        ],
        [
            1.0,
            0.0
        ],
        [
            0.92,
            0.08
        ],
        [
            1.0,
            0.0
        ],
        [
            0.94,
            0.06
        ],
        [
            0.99,
            0.01
        ],
        [
            0.92,
            0.08
        ],
        [
            0.98,
            0.02
        ]
    ],
    "y_pred": [
        0,
        0,
        0,
        0,
        0,
        0,
        0,
        0,
        0,
        0,
        0,
        0,
        0,
        0,
        0,
        0,
        0,
        0,
        0,
        0,
        0,
        0,
        0,
        0,
        0,
        0,
        0,
        0,
        0,
        0,
        0,
        0,
        0,
        0,
        0,
        0,
        0,
        0,
        0,
        0,
        0,
        0,
        0,
        0,
        0,
        0,
        0,
        0,
        0,
        0,
        0,
        0,
        0,
        0,
        0,
        0,
        0,
        0,
        0,
        0,
        0,
        0,
        0,
        0,
        0,
        0,
        0,
        0,
        0,
        0,
        0,
        0,
        0,
        0,
        0,
        0,
        0,
        0,
        0,
        0,
        0,
        0,
        0,
        0,
        0,
        0,
        0,
        0,
        0,
        0,
        0,
        0,
        0,
        0,
        0,
        0,
        0,
        0,
        0,
        0,
        0,
        0,
        0,
        0,
        0,
        0,
        0,
        0,
        0,
        0,
        0,
        0,
        0,
        0,
        0,
        0,
        0,
        0,
        0,
        0,
        0,
        0,
        0,
        0,
        0,
        0,
        0,
        0,
        0,
        0,
        0,
        0,
        0
    ],
    "y_test": [
        0,
        0,
        0,
        0,
        0,
        0,
        0,
        1,
        0,
        0,
        0,
        0,
        0,
        0,
        0,
        0,
        0,
        0,
        0,
        0,
        0,
        0,
        0,
        0,
        0,
        0,
        0,
        0,
        0,
        0,
        0,
        0,
        1,
        0,
        0,
        0,
        0,
        0,
        0,
        0,
        0,
        0,
        0,
        0,
        0,
        0,
        0,
        0,
        1,
        0,
        0,
        0,
        0,
        0,
        0,
        0,
        0,
        0,
        0,
        0,
        0,
        0,
        0,
        0,
        0,
        0,
        0,
        0,
        0,
        0,
        0,
        0,
        0,
        0,
        0,
        0,
        0,
        0,
        1,
        0,
        0,
        0,
        0,
        0,
        0,
        0,
        0,
        0,
        0,
        0,
        0,
        0,
        0,
        0,
        0,
        0,
        0,
        0,
        0,
        0,
        0,
        0,
        0,
        0,
        0,
        0,
        0,
        0,
        0,
        0,
        0,
        0,
        0,
        0,
        0,
        0,
        0,
        0,
        0,
        0,
        0,
        0,
        0,
        0,
        0,
        0,
        0,
        0,
        0,
        1,
        0,
        0,
        0
    ],
    "train_accuracy": 1.0,
    "train_auprc": 1.0,
    "train_auroc": 1.0,
    "accuracy": 0.9624060150375939,
    "auprc": 0.28685861941675894,
    "auroc": 0.7921875
}